aiowinreg/__init__.py
aiowinreg/__main__.py
aiowinreg/_version.py
aiowinreg/ahive.py
aiowinreg/hive.py
aiowinreg/examples/__init__.py
aiowinreg/examples/console.py
aiowinreg/external/__init__.py
aiowinreg/external/aiocmd/__init__.py
aiowinreg/external/aiocmd/setup.py
aiowinreg/external/aiocmd/aiocmd/__init__.py
aiowinreg/external/aiocmd/aiocmd/aiocmd.py
aiowinreg/external/aiocmd/aiocmd/nested_completer.py
aiowinreg/filestruct/__init__.py
aiowinreg/filestruct/hashrecord.py
aiowinreg/filestruct/hbin.py
aiowinreg/filestruct/header.py
aiowinreg/filestruct/keytypes.py
aiowinreg/filestruct/lf.py
aiowinreg/filestruct/lh.py
aiowinreg/filestruct/nk.py
aiowinreg/filestruct/regcell.py
aiowinreg/filestruct/ri.py
aiowinreg/filestruct/sk.py
aiowinreg/filestruct/valuelist.py
aiowinreg/filestruct/vk.py
aiowinreg/utils/__init__.py
aiowinreg/utils/afile.py
aiowinreg/utils/regcmdpathcompleter.py
aiowinreg-0.0.11.dist-info/LICENSE
aiowinreg-0.0.11.dist-info/METADATA
aiowinreg-0.0.11.dist-info/WHEEL
aiowinreg-0.0.11.dist-info/entry_points.txt
aiowinreg-0.0.11.dist-info/top_level.txt
aiowinreg-0.0.11.dist-info/zip-safe
aiowinreg-0.0.11.dist-info/RECORD
