Metadata-Version: 2.1
Name: aiowinreg
Version: 0.0.11
Summary: Windows registry file reader
Home-page: https://github.com/skelsec/aiowinreg
Author: Tamas Jos
Author-email: info@skelsecprojects.com
License: UNKNOWN
Platform: UNKNOWN
Classifier: Programming Language :: Python :: 3.6
Classifier: License :: OSI Approved :: MIT License
Classifier: Operating System :: OS Independent
Requires-Python: >=3.6
License-File: LICENSE
Requires-Dist: prompt-toolkit (>=3.0.2)
Requires-Dist: winacl (>=0.1.7)
